{
  "categories": [
    {
      "idCategory": 1, 
      "strCategory": "running"
    },
    {
    "idCategory": 2,
    "strCategory": "football"
    },
    {
    "idCategory": 3,
    "strCategory": "basketball"
    },
    {
    "idCategory": 4,
    "strCategory": "volleyball"
    },
    {
    "idCategory": 5,
    "strCategory": "handball"
    },
    {
    "idCategory": 6,
    "strCategory": "swimming"
    },
    {
    "idCategory": 7,
    "strCategory": "marcialarts"
    },
    {
    "idCategory": 8,
    "strCategory": "boxing"
    }
  ]
}
